{
    "GG": "Grundgesetz für die Bundesrepublik Deutschland",
    "BGB": "Bürgerliches Gesetzbuch",
    "StGB": "Strafgesetzbuch",
    "ZPO": "Zivilprozessordnung",
    "ArbZG": "Arbeitszeitgesetz",
    "KSchG": "Kündigungsschutzgesetz",
    "BetrVG": "Betriebsverfassungsgesetz",
    "AGG": "Allgemeines Gleichbehandlungsgesetz",
    "DSGVO": "Datenschutz-Grundverordnung",
    "BDSG": "Bundesdatenschutzgesetz",
    "DDG": "Digitale-Dienste-Gesetz",
    "UrhG": "Urheberrechtsgesetz",
    "BSIG": "Bundesamt für Sicherheit in der Informationstechnik",
    "GeschGehG": "Geschäftsgeheimnisgesetz",
    "GewO": "Gewerbeordnung",
    "HGB": "Handelsgesetzbuch",
    "GmbHG": "Gesetz betreffend die Gesellschaften mit beschränkter Haftung",
    "OWiG": "Gesetz über Ordnungswidrigkeiten",
    "AktG": "Aktiengesetz",
    "AufenthG": "Aufenthaltsgesetz",
    "AufenthV": "Aufenthaltsverordnung",
    "WoGG": "Wohngeldgesetz",
    "FreizügG/EU": "Freizügigkeit von Europäischen Unionsbürgern",
    "BAföG": "Bundesgesetz über individuelle Förderung der Ausbildung",
    "AO": "Abgabenordnung",
    "EStG": "Einkommensteuergesetz",
    "StVO": "Straßenverkehrsordnung",
    "SGB 1": "Erstes Buch Sozialgesetzbuch (Allgemeiner Teil)",
    "SGB 2": "Zweites Buch Sozialgesetzbuch (Bürgergeld, Grundsicherung für Arbeitsuchende)",
    "SGB 3": "Drittes Buch Sozialgesetzbuch (Arbeitsförderung)",
    "SGB 4": "Viertes Buch Sozialgesetzbuch (Gemeinsame Vorschriften für die Sozialversicherung)",
    "SGB 5": "Fünftes Buch Sozialgesetzbuch (Gesetzliche Krankenversicherung)",
    "SGB 9": "Neuntes Buch Sozialgesetzbuch (Rehabilitation und Teilhabe von Menschen mit Behinderungen)",
    "SGB 10": "Zehntes Buch Sozialgesetzbuch (Sozialverwaltungsverfahren und Sozialdatenschutz)"
}